octoparse/__init__.py
octoparse/__version__.py
octoparse/octoparse.py
octoparse-1.6.0.dist-info/LICENSE
octoparse-1.6.0.dist-info/METADATA
octoparse-1.6.0.dist-info/WHEEL
octoparse-1.6.0.dist-info/top_level.txt
octoparse-1.6.0.dist-info/RECORD
