Metadata-Version: 2.1
Name: octoparse
Version: 1.6.0
Summary: Unofficial Octoparse API client.
Home-page: https://github.com/itzmestar/Octoparse
Author: Tarique Anwer
Author-email: itzmetariq@gmail.com
License: Apache License 2.0
Platform: UNKNOWN
Classifier: Programming Language :: Python :: 3
Classifier: Programming Language :: Python :: 3.6
Classifier: Programming Language :: Python :: 3.7
Classifier: Programming Language :: Python :: 3.8
Classifier: Programming Language :: Python :: 3.9
Classifier: License :: OSI Approved :: Apache Software License
Classifier: Operating System :: OS Independent
Requires-Dist: requests (>=2.18.4)
Requires-Dist: pandas (>=0.23.4)
Requires-Dist: python-dotenv (>=0.15.0)
